README.md
dataloader.py
setup.py
PyDataLoader.egg-info/PKG-INFO
PyDataLoader.egg-info/SOURCES.txt
PyDataLoader.egg-info/dependency_links.txt
PyDataLoader.egg-info/namespace_packages.txt
PyDataLoader.egg-info/requires.txt
PyDataLoader.egg-info/top_level.txt
PyDataLoader.egg-info/zip-safe