Metadata-Version: 1.1
Name: PyDataLoader
Version: 0.1.2
Summary: Extensible JSON/YAML/RAML/... data loader
Home-page: https://github.com/salsita/pydataloader
Author: Salsita Software
Author-email: python@salsitasoft.com
License: MIT
Download-URL: https://github.com/salsita/pydataloader/tarball/v0.1.2
Keywords: data,load,YAML,RAML,JSON
Platform: any
Classifier: Development Status :: 4 - Beta
Classifier: Operating System :: OS Independent
Classifier: Intended Audience :: Developers
Classifier: Programming Language :: Python
Classifier: Programming Language :: Python :: 2.6
Classifier: Programming Language :: Python :: 2.7
Classifier: Programming Language :: Python :: 3.3
Classifier: Programming Language :: Python :: 3.4
Classifier: License :: OSI Approved :: MIT License
Classifier: Topic :: Text Processing :: Markup
Classifier: Topic :: Software Development :: Libraries :: Python Modules
